ezufw/__init__.py
ezufw/ezufw.py
ezufw-0.0.9.dist-info/LICENSE
ezufw-0.0.9.dist-info/METADATA
ezufw-0.0.9.dist-info/WHEEL
ezufw-0.0.9.dist-info/top_level.txt
ezufw-0.0.9.dist-info/RECORD
