Metadata-Version: 2.1
Name: ezufw
Version: 0.0.9
Summary: UFW Wrapper
Home-page: UNKNOWN
Author: Marek Adam Gancarz
Author-email: 
License: UNKNOWN
Keywords: python,python3,ufw,firewall
Platform: UNKNOWN
Classifier: Programming Language :: Python :: 3
Classifier: Operating System :: Unix
License-File: LICENSE
